setup.cfg
setup.py
pymogile/__init__.py
pymogile/admin.py
pymogile/backend.py
pymogile/client.py
pymogile/exceptions.py
pymogile/file.py
pymogile/local.py
pymogile/put.py
pymogile.egg-info/PKG-INFO
pymogile.egg-info/SOURCES.txt
pymogile.egg-info/dependency_links.txt
pymogile.egg-info/not-zip-safe
pymogile.egg-info/top_level.txt