Metadata-Version: 1.1
Name: pymogile
Version: 2.1.0
Summary: pymogile
Home-page: UNKNOWN
Author: stefanfoulis
Author-email: stefan.foulis@gmail.com
License: GPL
Platform: UNKNOWN
Classifier: Development Status :: 4 - Beta
Classifier: Intended Audience :: Developers
Classifier: License :: OSI Approved :: GNU General Public License (GPL)
Classifier: Operating System :: OS Independent
Classifier: Programming Language :: Python
Classifier: Topic :: Software Development :: Libraries :: Python Modules
